ChangePointDetector/ChangePointDetector.py
ChangePointDetector/__init__.py
ChangePointDetectorEVT-0.0.18.dist-info/LICENSE.txt
ChangePointDetectorEVT-0.0.18.dist-info/METADATA
ChangePointDetectorEVT-0.0.18.dist-info/WHEEL
ChangePointDetectorEVT-0.0.18.dist-info/top_level.txt
ChangePointDetectorEVT-0.0.18.dist-info/RECORD
