Metadata-Version: 2.1
Name: ChangePointDetectorEVT
Version: 0.0.18
Summary: This module takes a date time series and returns: (a) the underlaying linear trend and (b) the times where there is a change in the trend
Home-page: https://github.com/mhaupt63/ChangePointDetector
Author: Michael Hauptman
Author-email: michael.hauptman1@gmail.com
License: UNKNOWN
Project-URL: Bug Tracker, https://github.com/mhaupt63/ChangePointDetectorissues
Keywords: ['Time Series','Anomaly','Detection','Kalman','EVT']
Platform: UNKNOWN
Classifier: Development Status :: 3 - Alpha
Classifier: Programming Language :: Python :: 3
Classifier: License :: OSI Approved :: MIT License
Classifier: Operating System :: OS Independent
Requires-Python: >=3.7
License-File: LICENSE.txt
